catenae/__init__.py
catenae/callback.py
catenae/custom_multiprocessing.py
catenae/custom_queue.py
catenae/custom_threading.py
catenae/electron.py
catenae/link.py
catenae/logger.py
catenae/structures.py
catenae/utils.py
catenae/connectors/__init__.py
catenae/connectors/aerospike.py
catenae/connectors/mongodb.py
catenae-1.0.0.dist-info/LICENSE
catenae-1.0.0.dist-info/METADATA
catenae-1.0.0.dist-info/WHEEL
catenae-1.0.0.dist-info/top_level.txt
catenae-1.0.0.dist-info/RECORD
